{
    "info": {
        "description": "Building Instances Segmentation Dataset",
        "url": "",
        "version": "1.0.0",
        "year": 2022,
        "contributor": "JichongYin",
        "date_created": "2022-06-13 01:39:37.267311"
    },
    "licenses": [
        {
            "id": 1,
            "name": "",
            "url": ""
        }
    ],
    "images": [
        {
            "id": 87,
            "file_name": "1139.tif",
            "width": 1024,
            "height": 1024,
            "date_captured": "2022-06-13 01:39:35.548445",
            "license": 1,
            "coco_url": "",
            "flickr_url": ""
        }
    ],
    "categories": [
        {
            "id": 1,
            "name": "building",
            "supercategory": "building"
        }
    ],
    "annotations": [
        {
            "id": 476,
            "image_id": 87,
            "category_id": 1,
            "iscrowd": 0,
            "area": 34730,
            "bbox": [
                0.0,
                675.0,
                293.0,
                144.0
            ],
            "segmentation": [
                [
                    262.0,
                    818.5,
                    160.0,
                    812.5,
                    159.0,
                    802.5,
                    85.0,
                    798.5,
                    85.0,
                    780.5,
                    56.0,
                    778.5,
                    42.5,
                    779.0,
                    46.0,
                    806.5,
                    0.0,
                    803.5,
                    0,
                    682.0,
                    55.0,
                    683.5,
                    55.0,
                    693.5,
                    74.0,
                    694.5,
                    91.5,
                    694.0,
                    93.0,
                    674.5,
                    292.0,
                    686.5,
                    286.5,
                    792.0,
                    264.5,
                    792.0,
                    262.0,
                    818.5
                ]
            ],
            "width": 1024,
            "height": 1024
        },
        {
            "id": 477,
            "image_id": 87,
            "category_id": 1,
            "iscrowd": 0,
            "area": 3476,
            "bbox": [
                172.0,
                975.0,
                225.0,
                49.0
            ],
            "segmentation": [
                [
                    313.0,
                    1023.5,
                    171.5,
                    1023.0,
                    186.0,
                    974.5,
                    250.0,
                    993.5,
                    248.0,
                    1004.5,
                    313.0,
                    1023.5
                ],
                [
                    396.0,
                    1023.5,
                    387.5,
                    1023.0,
                    389.0,
                    1020.5,
                    396.0,
                    1023.5
                ]
            ],
            "width": 1024,
            "height": 1024
        },
        {
            "id": 478,
            "image_id": 87,
            "category_id": 1,
            "iscrowd": 0,
            "area": 38782,
            "bbox": [
                5.0,
                407.0,
                339.0,
                220.0
            ],
            "segmentation": [
                [
                    323.0,
                    626.5,
                    5.0,
                    518.5,
                    25.5,
                    458.0,
                    73.0,
                    473.5,
                    97.0,
                    406.5,
                    258.0,
                    461.5,
                    263.0,
                    452.5,
                    301.0,
                    465.5,
                    297.5,
                    478.0,
                    321.5,
                    487.0,
                    299.5,
                    552.0,
                    343.5,
                    567.0,
                    323.0,
                    626.5
                ]
            ],
            "width": 1024,
            "height": 1024
        },
        {
            "id": 479,
            "image_id": 87,
            "category_id": 1,
            "iscrowd": 0,
            "area": 50902,
            "bbox": [
                462.0,
                415.0,
                328.0,
                350.0
            ],
            "segmentation": [
                [
                    551.0,
                    764.5,
                    532.0,
                    737.5,
                    504.0,
                    754.5,
                    496.0,
                    741.5,
                    491.0,
                    745.5,
                    461.5,
                    698.0,
                    510.5,
                    667.0,
                    493.5,
                    639.0,
                    526.5,
                    618.0,
                    509.5,
                    593.0,
                    624.5,
                    520.0,
                    590.5,
                    466.0,
                    669.0,
                    415.5,
                    672.5,
                    416.0,
                    704.0,
                    468.5,
                    738.0,
                    446.5,
                    742.0,
                    452.5,
                    747.0,
                    449.5,
                    789.5,
                    517.0,
                    725.5,
                    557.0,
                    740.5,
                    581.0,
                    729.5,
                    588.0,
                    731.0,
                    591.5,
                    635.5,
                    653.0,
                    667.5,
                    703.0,
                    586.0,
                    755.5,
                    583.5,
                    756.0,
                    577.0,
                    746.5,
                    551.0,
                    764.5
                ]
            ],
            "width": 1024,
            "height": 1024
        },
        {
            "id": 480,
            "image_id": 87,
            "category_id": 1,
            "iscrowd": 0,
            "area": 4390,
            "bbox": [
                555.0,
                854.0,
                74.0,
                95.0
            ],
            "segmentation": [
                [
                    605.0,
                    948.5,
                    554.5,
                    933.0,
                    578.0,
                    853.5,
                    628.5,
                    869.0,
                    605.0,
                    948.5
                ]
            ],
            "width": 1024,
            "height": 1024
        },
        {
            "id": 481,
            "image_id": 87,
            "category_id": 1,
            "iscrowd": 0,
            "area": 36969,
            "bbox": [
                661.0,
                735.0,
                223.0,
                278.0
            ],
            "segmentation": [
                [
                    771.0,
                    1012.5,
                    739.0,
                    1011.5,
                    738.0,
                    1000.5,
                    665.5,
                    1000.0,
                    670.5,
                    869.0,
                    713.0,
                    868.5,
                    713.5,
                    856.0,
                    660.5,
                    796.0,
                    753.0,
                    734.5,
                    804.5,
                    792.0,
                    761.5,
                    830.0,
                    791.0,
                    860.5,
                    822.0,
                    860.5,
                    822.0,
                    876.5,
                    845.5,
                    877.0,
                    843.5,
                    952.0,
                    870.0,
                    952.5,
                    871.0,
                    959.5,
                    883.5,
                    960.0,
                    881.0,
                    1001.5,
                    867.0,
                    1000.5,
                    866.0,
                    1008.5,
                    772.0,
                    1005.5,
                    771.0,
                    1012.5
                ]
            ],
            "width": 1024,
            "height": 1024
        },
        {
            "id": 482,
            "image_id": 87,
            "category_id": 1,
            "iscrowd": 0,
            "area": 1328,
            "bbox": [
                173.0,
                28.0,
                50.0,
                43.0
            ],
            "segmentation": [
                [
                    213.0,
                    70.5,
                    172.5,
                    57.0,
                    181.0,
                    27.5,
                    222.5,
                    41.0,
                    213.0,
                    70.5
                ]
            ],
            "width": 1024,
            "height": 1024
        },
        {
            "id": 483,
            "image_id": 87,
            "category_id": 1,
            "iscrowd": 0,
            "area": 12717,
            "bbox": [
                348.0,
                502.0,
                138.0,
                159.0
            ],
            "segmentation": [
                [
                    436.0,
                    660.5,
                    347.5,
                    626.0,
                    397.0,
                    501.5,
                    485.5,
                    537.0,
                    436.0,
                    660.5
                ]
            ],
            "width": 1024,
            "height": 1024
        },
        {
            "id": 484,
            "image_id": 87,
            "category_id": 1,
            "iscrowd": 0,
            "area": 12642,
            "bbox": [
                802.0,
                0.0,
                159.0,
                126.0
            ],
            "segmentation": [
                [
                    882.0,
                    125.5,
                    812.5,
                    96.0,
                    833.5,
                    46.0,
                    801.5,
                    32.0,
                    813.5,
                    9.0,
                    814.5,
                    0.0,
                    960.0,
                    0,
                    934.5,
                    63.0,
                    922.5,
                    61.0,
                    907.5,
                    98.0,
                    894.5,
                    95.0,
                    882.0,
                    125.5
                ]
            ],
            "width": 1024,
            "height": 1024
        },
        {
            "id": 485,
            "image_id": 87,
            "category_id": 1,
            "iscrowd": 0,
            "area": 9425,
            "bbox": [
                663.0,
                37.0,
                106.0,
                181.0
            ],
            "segmentation": [
                [
                    732.0,
                    217.5,
                    662.5,
                    187.0,
                    729.0,
                    36.5,
                    760.5,
                    51.0,
                    730.5,
                    118.0,
                    768.5,
                    135.0,
                    732.0,
                    217.5
                ]
            ],
            "width": 1024,
            "height": 1024
        },
        {
            "id": 486,
            "image_id": 87,
            "category_id": 1,
            "iscrowd": 0,
            "area": 22517,
            "bbox": [
                402.0,
                52.0,
                233.0,
                171.0
            ],
            "segmentation": [
                [
                    587.0,
                    222.5,
                    509.0,
                    186.5,
                    498.0,
                    208.5,
                    402.0,
                    165.5,
                    437.5,
                    87.0,
                    477.0,
                    104.5,
                    502.0,
                    51.5,
                    552.0,
                    73.5,
                    550.0,
                    81.5,
                    634.0,
                    119.5,
                    587.0,
                    222.5
                ]
            ],
            "width": 1024,
            "height": 1024
        },
        {
            "id": 487,
            "image_id": 87,
            "category_id": 1,
            "iscrowd": 0,
            "area": 2294,
            "bbox": [
                629.0,
                221.0,
                70.0,
                59.0
            ],
            "segmentation": [
                [
                    683.0,
                    279.5,
                    628.5,
                    256.0,
                    644.0,
                    220.5,
                    698.5,
                    244.0,
                    683.0,
                    279.5
                ]
            ],
            "width": 1024,
            "height": 1024
        }
    ]
}