{
    "info": {
        "description": "Building Instances Segmentation Dataset",
        "url": "",
        "version": "1.0.0",
        "year": 2022,
        "contributor": "JichongYin",
        "date_created": "2022-06-13 01:39:37.267311"
    },
    "licenses": [
        {
            "id": 1,
            "name": "",
            "url": ""
        }
    ],
    "images": [
        {
            "id": 121,
            "file_name": "119.tif",
            "width": 1024,
            "height": 1024,
            "date_captured": "2022-06-13 01:39:35.548445",
            "license": 1,
            "coco_url": "",
            "flickr_url": ""
        }
    ],
    "categories": [
        {
            "id": 1,
            "name": "building",
            "supercategory": "building"
        }
    ],
    "annotations": [
        {
            "id": 707,
            "image_id": 121,
            "category_id": 1,
            "iscrowd": 0,
            "area": 4214,
            "bbox": [
                835.0,
                226.0,
                79.0,
                74.0
            ],
            "segmentation": [
                [
                    847.0,
                    299.5,
                    834.5,
                    238.0,
                    901.0,
                    225.5,
                    913.5,
                    286.0,
                    847.0,
                    299.5
                ]
            ],
            "width": 1024,
            "height": 1024
        },
        {
            "id": 708,
            "image_id": 121,
            "category_id": 1,
            "iscrowd": 0,
            "area": 35653,
            "bbox": [
                724.0,
                0.0,
                300.0,
                205.0
            ],
            "segmentation": [
                [
                    729.0,
                    204.5,
                    723.5,
                    169.0,
                    724.5,
                    158.0,
                    732.5,
                    141.0,
                    750.5,
                    127.0,
                    744.5,
                    81.0,
                    767.5,
                    78.0,
                    762.5,
                    29.0,
                    770.5,
                    15.0,
                    783.0,
                    4.5,
                    800.0,
                    0,
                    817.0,
                    1.5,
                    837.5,
                    16.0,
                    842.5,
                    28.0,
                    848.0,
                    81.5,
                    941.0,
                    71.5,
                    943.0,
                    81.5,
                    1018.5,
                    75.0,
                    1023.5,
                    107.0,
                    1023.0,
                    168.5,
                    932.0,
                    181.5,
                    929.5,
                    166.0,
                    924.0,
                    165.5,
                    873.0,
                    172.5,
                    874.0,
                    184.5,
                    729.0,
                    204.5
                ]
            ],
            "width": 1024,
            "height": 1024
        },
        {
            "id": 709,
            "image_id": 121,
            "category_id": 1,
            "iscrowd": 0,
            "area": 30201,
            "bbox": [
                407.0,
                0.0,
                235.0,
                193.0
            ],
            "segmentation": [
                [
                    606.0,
                    192.5,
                    497.0,
                    171.5,
                    492.5,
                    174.0,
                    490.0,
                    187.5,
                    406.5,
                    171.0,
                    425.0,
                    79.5,
                    491.0,
                    92.5,
                    494.5,
                    92.0,
                    496.0,
                    84.5,
                    512.5,
                    87.0,
                    516.5,
                    70.0,
                    498.5,
                    67.0,
                    512.0,
                    0,
                    641.5,
                    0.0,
                    606.0,
                    192.5
                ]
            ],
            "width": 1024,
            "height": 1024
        },
        {
            "id": 710,
            "image_id": 121,
            "category_id": 1,
            "iscrowd": 0,
            "area": 23229,
            "bbox": [
                214.0,
                0.0,
                201.0,
                163.0
            ],
            "segmentation": [
                [
                    346.0,
                    162.5,
                    287.0,
                    151.5,
                    289.0,
                    134.5,
                    213.5,
                    121.0,
                    229.5,
                    37.0,
                    296.0,
                    48.5,
                    299.5,
                    30.0,
                    280.5,
                    27.0,
                    286.0,
                    0,
                    414.0,
                    0,
                    385.5,
                    156.0,
                    349.0,
                    149.5,
                    346.0,
                    162.5
                ]
            ],
            "width": 1024,
            "height": 1024
        },
        {
            "id": 711,
            "image_id": 121,
            "category_id": 1,
            "iscrowd": 0,
            "area": 8006,
            "bbox": [
                125.0,
                472.0,
                100.0,
                97.0
            ],
            "segmentation": [
                [
                    133.0,
                    568.5,
                    124.5,
                    482.0,
                    215.0,
                    471.5,
                    224.5,
                    559.0,
                    133.0,
                    568.5
                ]
            ],
            "width": 1024,
            "height": 1024
        },
        {
            "id": 712,
            "image_id": 121,
            "category_id": 1,
            "iscrowd": 0,
            "area": 30150,
            "bbox": [
                9.0,
                711.0,
                207.0,
                204.0
            ],
            "segmentation": [
                [
                    180.0,
                    914.5,
                    8.5,
                    879.0,
                    44.0,
                    710.5,
                    215.5,
                    746.0,
                    180.0,
                    914.5
                ]
            ],
            "width": 1024,
            "height": 1024
        },
        {
            "id": 713,
            "image_id": 121,
            "category_id": 1,
            "iscrowd": 0,
            "area": 44797,
            "bbox": [
                435.0,
                547.0,
                215.0,
                386.0
            ],
            "segmentation": [
                [
                    556.0,
                    932.5,
                    472.5,
                    901.0,
                    498.5,
                    834.0,
                    450.5,
                    817.0,
                    467.5,
                    769.0,
                    454.0,
                    764.5,
                    456.5,
                    757.0,
                    437.0,
                    750.5,
                    434.5,
                    742.0,
                    435.5,
                    727.0,
                    439.5,
                    718.0,
                    455.0,
                    701.5,
                    474.0,
                    708.5,
                    479.0,
                    699.5,
                    489.0,
                    703.5,
                    492.5,
                    700.0,
                    504.5,
                    667.0,
                    471.5,
                    653.0,
                    513.0,
                    546.5,
                    649.5,
                    599.0,
                    629.5,
                    650.0,
                    635.5,
                    655.0,
                    562.5,
                    842.0,
                    587.5,
                    853.0,
                    556.0,
                    932.5
                ]
            ],
            "width": 1024,
            "height": 1024
        },
        {
            "id": 714,
            "image_id": 121,
            "category_id": 1,
            "iscrowd": 0,
            "area": 21936,
            "bbox": [
                615.0,
                882.0,
                241.0,
                142.0
            ],
            "segmentation": [
                [
                    835.0,
                    1023.5,
                    651.0,
                    1023.5,
                    615.0,
                    1009.5,
                    661.5,
                    882.0,
                    737.0,
                    909.5,
                    732.0,
                    928.5,
                    801.0,
                    954.5,
                    811.0,
                    932.5,
                    855.0,
                    948.5,
                    843.5,
                    982.0,
                    849.5,
                    986.0,
                    835.0,
                    1023.5
                ]
            ],
            "width": 1024,
            "height": 1024
        },
        {
            "id": 715,
            "image_id": 121,
            "category_id": 1,
            "iscrowd": 0,
            "area": 1790,
            "bbox": [
                636.0,
                152.0,
                50.0,
                50.0
            ],
            "segmentation": [
                [
                    676.0,
                    201.5,
                    635.5,
                    194.0,
                    645.0,
                    151.5,
                    685.5,
                    159.0,
                    676.0,
                    201.5
                ]
            ],
            "width": 1024,
            "height": 1024
        }
    ]
}