{
    "info": {
        "description": "Building Instances Segmentation Dataset",
        "url": "",
        "version": "1.0.0",
        "year": 2022,
        "contributor": "JichongYin",
        "date_created": "2022-06-13 01:39:37.267311"
    },
    "licenses": [
        {
            "id": 1,
            "name": "",
            "url": ""
        }
    ],
    "images": [
        {
            "id": 252,
            "file_name": "1384.tif",
            "width": 1024,
            "height": 1024,
            "date_captured": "2022-06-13 01:39:35.548445",
            "license": 1,
            "coco_url": "",
            "flickr_url": ""
        }
    ],
    "categories": [
        {
            "id": 1,
            "name": "building",
            "supercategory": "building"
        }
    ],
    "annotations": [
        {
            "id": 1275,
            "image_id": 252,
            "category_id": 1,
            "iscrowd": 0,
            "area": 68697,
            "bbox": [
                367.0,
                233.0,
                483.0,
                349.0
            ],
            "segmentation": [
                [
                    498.0,
                    581.5,
                    469.0,
                    537.5,
                    390.0,
                    521.5,
                    382.0,
                    511.5,
                    376.5,
                    512.0,
                    366.5,
                    495.0,
                    375.5,
                    449.0,
                    408.0,
                    431.5,
                    417.5,
                    433.0,
                    424.0,
                    399.5,
                    460.0,
                    406.5,
                    464.0,
                    406.5,
                    466.0,
                    401.5,
                    499.0,
                    407.5,
                    505.0,
                    374.5,
                    557.0,
                    383.5,
                    577.0,
                    413.5,
                    594.0,
                    402.5,
                    642.0,
                    475.5,
                    755.5,
                    402.0,
                    744.5,
                    237.0,
                    836.0,
                    232.5,
                    849.5,
                    448.0,
                    654.0,
                    574.5,
                    610.0,
                    507.5,
                    498.0,
                    581.5
                ]
            ],
            "width": 1024,
            "height": 1024
        },
        {
            "id": 1276,
            "image_id": 252,
            "category_id": 1,
            "iscrowd": 0,
            "area": 4140,
            "bbox": [
                976.0,
                112.0,
                48.0,
                100.0
            ],
            "segmentation": [
                [
                    1023.0,
                    211.5,
                    976.5,
                    208.0,
                    975.5,
                    147.0,
                    989.5,
                    146.0,
                    990.0,
                    111.5,
                    1023.5,
                    115.0,
                    1023.0,
                    211.5
                ]
            ],
            "width": 1024,
            "height": 1024
        },
        {
            "id": 1277,
            "image_id": 252,
            "category_id": 1,
            "iscrowd": 0,
            "area": 47664,
            "bbox": [
                710.0,
                696.0,
                282.0,
                328.0
            ],
            "segmentation": [
                [
                    863.0,
                    1023.5,
                    852.0,
                    1023.5,
                    849.5,
                    1021.0,
                    719.5,
                    821.0,
                    743.5,
                    805.0,
                    709.5,
                    753.0,
                    802.0,
                    695.5,
                    815.0,
                    715.5,
                    827.5,
                    711.0,
                    859.0,
                    762.5,
                    929.0,
                    718.5,
                    991.5,
                    810.0,
                    915.5,
                    856.0,
                    904.5,
                    909.0,
                    923.5,
                    938.0,
                    911.5,
                    947.0,
                    915.0,
                    952.5,
                    888.5,
                    970.0,
                    904.5,
                    996.0,
                    863.0,
                    1023.5
                ]
            ],
            "width": 1024,
            "height": 1024
        }
    ]
}