{
    "info": {
        "description": "Building Instances Segmentation Dataset",
        "url": "",
        "version": "1.0.0",
        "year": 2022,
        "contributor": "JichongYin",
        "date_created": "2022-06-13 01:39:37.267311"
    },
    "licenses": [
        {
            "id": 1,
            "name": "",
            "url": ""
        }
    ],
    "images": [
        {
            "id": 372,
            "file_name": "1571.tif",
            "width": 1024,
            "height": 1024,
            "date_captured": "2022-06-13 01:39:35.548445",
            "license": 1,
            "coco_url": "",
            "flickr_url": ""
        }
    ],
    "categories": [
        {
            "id": 1,
            "name": "building",
            "supercategory": "building"
        }
    ],
    "annotations": [
        {
            "id": 1621,
            "image_id": 372,
            "category_id": 1,
            "iscrowd": 0,
            "area": 7374,
            "bbox": [
                0.0,
                823.0,
                66.0,
                201.0
            ],
            "segmentation": [
                [
                    65.0,
                    1023.5,
                    0,
                    1023.0,
                    0.0,
                    822.5,
                    17.5,
                    823.0,
                    18.5,
                    855.0,
                    29.5,
                    855.0,
                    33.5,
                    981.0,
                    63.5,
                    981.0,
                    65.0,
                    1023.5
                ]
            ],
            "width": 1024,
            "height": 1024
        },
        {
            "id": 1622,
            "image_id": 372,
            "category_id": 1,
            "iscrowd": 0,
            "area": 23957,
            "bbox": [
                302.0,
                362.0,
                159.0,
                225.0
            ],
            "segmentation": [
                [
                    304.0,
                    586.5,
                    301.5,
                    510.0,
                    349.5,
                    509.0,
                    346.5,
                    391.0,
                    392.0,
                    390.5,
                    392.0,
                    362.5,
                    448.0,
                    361.5,
                    449.5,
                    388.0,
                    457.5,
                    389.0,
                    460.5,
                    550.0,
                    380.0,
                    550.5,
                    380.0,
                    585.5,
                    304.0,
                    586.5
                ]
            ],
            "width": 1024,
            "height": 1024
        },
        {
            "id": 1623,
            "image_id": 372,
            "category_id": 1,
            "iscrowd": 0,
            "area": 3250,
            "bbox": [
                532.0,
                290.0,
                55.0,
                64.0
            ],
            "segmentation": [
                [
                    534.0,
                    353.5,
                    531.5,
                    292.0,
                    584.0,
                    289.5,
                    586.5,
                    351.0,
                    534.0,
                    353.5
                ]
            ],
            "width": 1024,
            "height": 1024
        },
        {
            "id": 1624,
            "image_id": 372,
            "category_id": 1,
            "iscrowd": 0,
            "area": 26126,
            "bbox": [
                534.0,
                489.0,
                234.0,
                121.0
            ],
            "segmentation": [
                [
                    534.0,
                    609.5,
                    534.0,
                    497.5,
                    619.0,
                    497.5,
                    620.0,
                    489.5,
                    755.5,
                    491.0,
                    756.5,
                    534.0,
                    766.5,
                    535.0,
                    767.0,
                    605.5,
                    534.0,
                    609.5
                ]
            ],
            "width": 1024,
            "height": 1024
        },
        {
            "id": 1625,
            "image_id": 372,
            "category_id": 1,
            "iscrowd": 0,
            "area": 27521,
            "bbox": [
                214.0,
                813.0,
                220.0,
                191.0
            ],
            "segmentation": [
                [
                    260.0,
                    1003.5,
                    259.0,
                    985.5,
                    217.5,
                    987.0,
                    213.5,
                    886.0,
                    349.0,
                    880.5,
                    348.0,
                    815.5,
                    426.0,
                    812.5,
                    433.5,
                    977.0,
                    297.0,
                    982.5,
                    297.0,
                    1002.5,
                    260.0,
                    1003.5
                ]
            ],
            "width": 1024,
            "height": 1024
        },
        {
            "id": 1626,
            "image_id": 372,
            "category_id": 1,
            "iscrowd": 0,
            "area": 2800,
            "bbox": [
                352.0,
                990.0,
                87.0,
                34.0
            ],
            "segmentation": [
                [
                    438.0,
                    1023.5,
                    353.0,
                    1023.5,
                    351.5,
                    992.0,
                    437.0,
                    989.5,
                    438.0,
                    1023.5
                ]
            ],
            "width": 1024,
            "height": 1024
        },
        {
            "id": 1627,
            "image_id": 372,
            "category_id": 1,
            "iscrowd": 0,
            "area": 24984,
            "bbox": [
                493.0,
                847.0,
                210.0,
                177.0
            ],
            "segmentation": [
                [
                    702.0,
                    1023.5,
                    493.5,
                    1023.0,
                    493.0,
                    981.5,
                    580.5,
                    980.0,
                    579.0,
                    848.5,
                    699.5,
                    847.0,
                    702.0,
                    1023.5
                ]
            ],
            "width": 1024,
            "height": 1024
        },
        {
            "id": 1628,
            "image_id": 372,
            "category_id": 1,
            "iscrowd": 0,
            "area": 9469,
            "bbox": [
                893.0,
                641.0,
                117.0,
                125.0
            ],
            "segmentation": [
                [
                    931.0,
                    765.5,
                    927.0,
                    757.5,
                    915.0,
                    762.5,
                    904.5,
                    739.0,
                    902.5,
                    733.0,
                    914.5,
                    727.0,
                    892.5,
                    671.0,
                    911.5,
                    664.0,
                    908.0,
                    651.5,
                    933.0,
                    641.5,
                    936.5,
                    641.0,
                    943.0,
                    652.5,
                    972.0,
                    640.5,
                    1009.5,
                    734.0,
                    931.0,
                    765.5
                ]
            ],
            "width": 1024,
            "height": 1024
        },
        {
            "id": 1629,
            "image_id": 372,
            "category_id": 1,
            "iscrowd": 0,
            "area": 1084,
            "bbox": [
                998.0,
                640.0,
                26.0,
                74.0
            ],
            "segmentation": [
                [
                    1017.0,
                    713.5,
                    1008.5,
                    696.0,
                    1015.5,
                    691.0,
                    997.5,
                    650.0,
                    1023.0,
                    639.5,
                    1023.5,
                    710.0,
                    1017.0,
                    713.5
                ]
            ],
            "width": 1024,
            "height": 1024
        },
        {
            "id": 1630,
            "image_id": 372,
            "category_id": 1,
            "iscrowd": 0,
            "area": 18766,
            "bbox": [
                854.0,
                878.0,
                156.0,
                146.0
            ],
            "segmentation": [
                [
                    986.0,
                    1023.5,
                    879.5,
                    1023.0,
                    876.5,
                    967.0,
                    857.5,
                    967.0,
                    854.0,
                    885.5,
                    1005.5,
                    878.0,
                    1009.5,
                    959.0,
                    982.5,
                    961.0,
                    986.0,
                    1023.5
                ]
            ],
            "width": 1024,
            "height": 1024
        },
        {
            "id": 1631,
            "image_id": 372,
            "category_id": 1,
            "iscrowd": 0,
            "area": 7716,
            "bbox": [
                397.0,
                163.0,
                92.0,
                92.0
            ],
            "segmentation": [
                [
                    401.0,
                    254.5,
                    396.5,
                    167.0,
                    484.0,
                    162.5,
                    488.5,
                    251.0,
                    401.0,
                    254.5
                ]
            ],
            "width": 1024,
            "height": 1024
        }
    ]
}