{
    "info": {
        "description": "Building Instances Segmentation Dataset",
        "url": "",
        "version": "1.0.0",
        "year": 2022,
        "contributor": "JichongYin",
        "date_created": "2022-06-13 01:39:37.267311"
    },
    "licenses": [
        {
            "id": 1,
            "name": "",
            "url": ""
        }
    ],
    "images": [
        {
            "id": 835,
            "file_name": "705.tif",
            "width": 1024,
            "height": 1024,
            "date_captured": "2022-06-13 01:39:35.548445",
            "license": 1,
            "coco_url": "",
            "flickr_url": ""
        }
    ],
    "categories": [
        {
            "id": 1,
            "name": "building",
            "supercategory": "building"
        }
    ],
    "annotations": [
        {
            "id": 3434,
            "image_id": 835,
            "category_id": 1,
            "iscrowd": 0,
            "area": 12237,
            "bbox": [
                0.0,
                369.0,
                132.0,
                122.0
            ],
            "segmentation": [
                [
                    3.0,
                    490.5,
                    0,
                    490.0,
                    0,
                    391.0,
                    112.0,
                    368.5,
                    131.5,
                    465.0,
                    3.0,
                    490.5
                ]
            ],
            "width": 1024,
            "height": 1024
        },
        {
            "id": 3435,
            "image_id": 835,
            "category_id": 1,
            "iscrowd": 0,
            "area": 5524,
            "bbox": [
                0.0,
                0.0,
                123.0,
                58.0
            ],
            "segmentation": [
                [
                    2.0,
                    57.5,
                    0,
                    57.0,
                    0.0,
                    0,
                    116.5,
                    0.0,
                    122.0,
                    33.5,
                    2.0,
                    57.5
                ]
            ],
            "width": 1024,
            "height": 1024
        },
        {
            "id": 3436,
            "image_id": 835,
            "category_id": 1,
            "iscrowd": 0,
            "area": 13378,
            "bbox": [
                0.0,
                105.0,
                149.0,
                116.0
            ],
            "segmentation": [
                [
                    1.0,
                    220.5,
                    0.0,
                    116.5,
                    62.0,
                    104.5,
                    101.0,
                    118.5,
                    99.0,
                    126.5,
                    144.5,
                    152.0,
                    148.5,
                    183.0,
                    139.5,
                    184.0,
                    141.0,
                    204.5,
                    69.0,
                    216.5,
                    67.5,
                    210.0,
                    63.0,
                    209.5,
                    1.0,
                    220.5
                ]
            ],
            "width": 1024,
            "height": 1024
        },
        {
            "id": 3437,
            "image_id": 835,
            "category_id": 1,
            "iscrowd": 0,
            "area": 39,
            "bbox": [
                338.0,
                0.0,
                25.0,
                3.0
            ],
            "segmentation": [
                [
                    362.0,
                    2.5,
                    337.5,
                    0.0,
                    362.0,
                    0,
                    362.0,
                    2.5
                ]
            ],
            "width": 1024,
            "height": 1024
        },
        {
            "id": 3438,
            "image_id": 835,
            "category_id": 1,
            "iscrowd": 0,
            "area": 10215,
            "bbox": [
                0.0,
                232.0,
                109.0,
                122.0
            ],
            "segmentation": [
                [
                    0.0,
                    353.5,
                    0,
                    251.0,
                    88.0,
                    231.5,
                    108.5,
                    331.0,
                    0.0,
                    353.5
                ]
            ],
            "width": 1024,
            "height": 1024
        },
        {
            "id": 3439,
            "image_id": 835,
            "category_id": 1,
            "iscrowd": 0,
            "area": 12022,
            "bbox": [
                0.0,
                525.0,
                121.0,
                126.0
            ],
            "segmentation": [
                [
                    4.0,
                    650.5,
                    0,
                    650.0,
                    0,
                    541.0,
                    62.0,
                    528.5,
                    62.5,
                    532.0,
                    66.0,
                    532.5,
                    102.0,
                    524.5,
                    120.5,
                    623.0,
                    80.0,
                    630.5,
                    80.0,
                    636.5,
                    4.0,
                    650.5
                ]
            ],
            "width": 1024,
            "height": 1024
        },
        {
            "id": 3440,
            "image_id": 835,
            "category_id": 1,
            "iscrowd": 0,
            "area": 21110,
            "bbox": [
                0.0,
                673.0,
                198.0,
                200.0
            ],
            "segmentation": [
                [
                    2.0,
                    872.5,
                    0,
                    872.0,
                    0,
                    761.0,
                    13.5,
                    758.0,
                    10.5,
                    742.0,
                    54.0,
                    733.5,
                    49.5,
                    709.0,
                    82.0,
                    702.5,
                    80.0,
                    684.5,
                    136.0,
                    672.5,
                    142.0,
                    692.5,
                    175.0,
                    685.5,
                    197.5,
                    793.0,
                    6.0,
                    831.5,
                    12.5,
                    870.0,
                    2.0,
                    872.5
                ]
            ],
            "width": 1024,
            "height": 1024
        },
        {
            "id": 3441,
            "image_id": 835,
            "category_id": 1,
            "iscrowd": 0,
            "area": 15200,
            "bbox": [
                74.0,
                851.0,
                162.0,
                129.0
            ],
            "segmentation": [
                [
                    92.0,
                    979.5,
                    73.5,
                    879.0,
                    126.0,
                    871.5,
                    126.0,
                    864.5,
                    147.0,
                    861.5,
                    149.0,
                    868.5,
                    162.0,
                    867.5,
                    162.0,
                    858.5,
                    216.0,
                    850.5,
                    235.5,
                    955.0,
                    145.0,
                    972.5,
                    140.0,
                    969.5,
                    92.0,
                    979.5
                ]
            ],
            "width": 1024,
            "height": 1024
        }
    ]
}