{
    "info": {
        "description": "Building Instances Segmentation Dataset",
        "url": "",
        "version": "1.0.0",
        "year": 2022,
        "contributor": "JichongYin",
        "date_created": "2022-06-13 01:39:37.267311"
    },
    "licenses": [
        {
            "id": 1,
            "name": "",
            "url": ""
        }
    ],
    "images": [
        {
            "id": 981,
            "file_name": "923.tif",
            "width": 1024,
            "height": 1024,
            "date_captured": "2022-06-13 01:39:35.548445",
            "license": 1,
            "coco_url": "",
            "flickr_url": ""
        }
    ],
    "categories": [
        {
            "id": 1,
            "name": "building",
            "supercategory": "building"
        }
    ],
    "annotations": [
        {
            "id": 4364,
            "image_id": 981,
            "category_id": 1,
            "iscrowd": 0,
            "area": 42385,
            "bbox": [
                490.0,
                769.0,
                417.0,
                199.0
            ],
            "segmentation": [
                [
                    692.0,
                    967.5,
                    556.0,
                    907.5,
                    567.0,
                    878.5,
                    489.5,
                    847.0,
                    522.0,
                    768.5,
                    602.0,
                    801.5,
                    608.0,
                    789.5,
                    688.0,
                    821.5,
                    681.5,
                    839.0,
                    716.0,
                    853.5,
                    737.0,
                    804.5,
                    788.0,
                    825.5,
                    792.0,
                    818.5,
                    847.0,
                    841.5,
                    905.5,
                    840.0,
                    859.0,
                    929.5,
                    795.0,
                    900.5,
                    766.0,
                    963.5,
                    706.0,
                    936.5,
                    692.0,
                    967.5
                ]
            ],
            "width": 1024,
            "height": 1024
        },
        {
            "id": 4365,
            "image_id": 981,
            "category_id": 1,
            "iscrowd": 0,
            "area": 817,
            "bbox": [
                505.0,
                991.0,
                48.0,
                33.0
            ],
            "segmentation": [
                [
                    552.0,
                    1023.5,
                    525.0,
                    1023.5,
                    517.5,
                    995.0,
                    541.0,
                    990.5,
                    552.0,
                    1023.5
                ]
            ],
            "width": 1024,
            "height": 1024
        },
        {
            "id": 4366,
            "image_id": 981,
            "category_id": 1,
            "iscrowd": 0,
            "area": 11555,
            "bbox": [
                326.0,
                0.0,
                223.0,
                103.0
            ],
            "segmentation": [
                [
                    393.0,
                    102.5,
                    326.0,
                    0,
                    548.5,
                    0.0,
                    393.0,
                    102.5
                ]
            ],
            "width": 1024,
            "height": 1024
        },
        {
            "id": 4367,
            "image_id": 981,
            "category_id": 1,
            "iscrowd": 0,
            "area": 32952,
            "bbox": [
                601.0,
                213.0,
                270.0,
                209.0
            ],
            "segmentation": [
                [
                    680.0,
                    421.5,
                    670.0,
                    397.5,
                    654.5,
                    403.0,
                    637.5,
                    359.0,
                    630.0,
                    360.5,
                    627.5,
                    356.0,
                    600.5,
                    286.0,
                    622.5,
                    273.0,
                    618.0,
                    260.5,
                    676.0,
                    237.5,
                    700.0,
                    295.5,
                    760.5,
                    271.0,
                    750.5,
                    246.0,
                    755.5,
                    242.0,
                    750.0,
                    228.5,
                    791.0,
                    212.5,
                    797.0,
                    223.5,
                    810.0,
                    218.5,
                    816.0,
                    234.5,
                    824.5,
                    233.0,
                    843.5,
                    283.0,
                    855.0,
                    280.5,
                    857.5,
                    285.0,
                    867.5,
                    311.0,
                    852.5,
                    318.0,
                    870.5,
                    362.0,
                    812.0,
                    385.5,
                    804.0,
                    371.5,
                    680.0,
                    421.5
                ]
            ],
            "width": 1024,
            "height": 1024
        },
        {
            "id": 4368,
            "image_id": 981,
            "category_id": 1,
            "iscrowd": 0,
            "area": 34031,
            "bbox": [
                473.0,
                0.0,
                374.0,
                229.0
            ],
            "segmentation": [
                [
                    522.0,
                    228.5,
                    501.5,
                    180.0,
                    493.0,
                    181.5,
                    490.5,
                    177.0,
                    474.5,
                    138.0,
                    481.5,
                    133.0,
                    473.0,
                    112.5,
                    544.0,
                    83.5,
                    546.0,
                    72.5,
                    557.0,
                    77.5,
                    566.0,
                    74.5,
                    575.0,
                    93.5,
                    627.0,
                    71.5,
                    633.0,
                    83.5,
                    672.0,
                    67.5,
                    674.5,
                    65.0,
                    664.5,
                    42.0,
                    718.0,
                    20.5,
                    710.0,
                    0,
                    825.5,
                    1.0,
                    846.0,
                    52.5,
                    794.0,
                    73.5,
                    786.0,
                    57.5,
                    724.0,
                    82.5,
                    734.0,
                    110.5,
                    644.5,
                    148.0,
                    656.0,
                    178.5,
                    598.0,
                    202.5,
                    595.0,
                    197.5,
                    592.0,
                    198.5,
                    522.0,
                    228.5
                ]
            ],
            "width": 1024,
            "height": 1024
        },
        {
            "id": 4369,
            "image_id": 981,
            "category_id": 1,
            "iscrowd": 0,
            "area": 23851,
            "bbox": [
                0.0,
                207.0,
                110.0,
                250.0
            ],
            "segmentation": [
                [
                    7.0,
                    456.5,
                    0,
                    456.0,
                    0,
                    216.0,
                    72.0,
                    206.5,
                    76.5,
                    234.0,
                    97.5,
                    233.0,
                    104.5,
                    286.0,
                    104.0,
                    289.5,
                    95.5,
                    290.0,
                    109.5,
                    406.0,
                    109.0,
                    410.5,
                    96.5,
                    412.0,
                    100.5,
                    445.0,
                    7.0,
                    456.5
                ]
            ],
            "width": 1024,
            "height": 1024
        },
        {
            "id": 4370,
            "image_id": 981,
            "category_id": 1,
            "iscrowd": 0,
            "area": 29681,
            "bbox": [
                0.0,
                509.0,
                141.0,
                242.0
            ],
            "segmentation": [
                [
                    117.0,
                    750.5,
                    17.0,
                    740.5,
                    16.0,
                    731.5,
                    0,
                    730.0,
                    0.0,
                    508.5,
                    140.5,
                    522.0,
                    117.0,
                    750.5
                ]
            ],
            "width": 1024,
            "height": 1024
        },
        {
            "id": 4371,
            "image_id": 981,
            "category_id": 1,
            "iscrowd": 0,
            "area": 8581,
            "bbox": [
                0.0,
                764.0,
                63.0,
                223.0
            ],
            "segmentation": [
                [
                    6.0,
                    986.5,
                    0,
                    982.0,
                    0.0,
                    763.5,
                    53.0,
                    783.5,
                    43.5,
                    799.0,
                    62.5,
                    811.0,
                    43.5,
                    841.0,
                    32.0,
                    837.5,
                    20.5,
                    855.0,
                    51.5,
                    875.0,
                    36.5,
                    897.0,
                    55.5,
                    910.0,
                    6.0,
                    986.5
                ]
            ],
            "width": 1024,
            "height": 1024
        }
    ]
}