<annotation>
  <folder>1</folder>
  <filename>721.tif</filename>
  <source>
    <database>CKdemo</database>
    <annotation>VOC</annotation>
    <image>CK</image>
  </source>
  <size>
    <width>1024</width>
    <height>1024</height>
    <depth>3</depth>
  </size>
  <segmented>0</segmented>
  <object>
    <name>building</name>
    <pose/>
    <truncated>0</truncated>
    <difficult>0</difficult>
    <bndbox>
      <xmin>58</xmin>
      <ymin>622</ymin>
      <xmax>257</xmax>
      <ymax>776</ymax>
    </bndbox>
  </object>
  <object>
    <name>building</name>
    <pose/>
    <truncated>0</truncated>
    <difficult>0</difficult>
    <bndbox>
      <xmin>313</xmin>
      <ymin>481</ymin>
      <xmax>670</xmax>
      <ymax>789</ymax>
    </bndbox>
  </object>
  <object>
    <name>building</name>
    <pose/>
    <truncated>0</truncated>
    <difficult>0</difficult>
    <bndbox>
      <xmin>680</xmin>
      <ymin>594</ymin>
      <xmax>892</xmax>
      <ymax>824</ymax>
    </bndbox>
  </object>
  <object>
    <name>building</name>
    <pose/>
    <truncated>0</truncated>
    <difficult>0</difficult>
    <bndbox>
      <xmin>266</xmin>
      <ymin>921</ymin>
      <xmax>521</xmax>
      <ymax>1024</ymax>
    </bndbox>
  </object>
  <object>
    <name>building</name>
    <pose/>
    <truncated>0</truncated>
    <difficult>0</difficult>
    <bndbox>
      <xmin>836</xmin>
      <ymin>0</ymin>
      <xmax>847</xmax>
      <ymax>6</ymax>
    </bndbox>
  </object>
  <object>
    <name>building</name>
    <pose/>
    <truncated>0</truncated>
    <difficult>0</difficult>
    <bndbox>
      <xmin>19</xmin>
      <ymin>330</ymin>
      <xmax>140</xmax>
      <ymax>455</ymax>
    </bndbox>
  </object>
  <object>
    <name>building</name>
    <pose/>
    <truncated>0</truncated>
    <difficult>0</difficult>
    <bndbox>
      <xmin>0</xmin>
      <ymin>0</ymin>
      <xmax>12</xmax>
      <ymax>3</ymax>
    </bndbox>
  </object>
</annotation>
